{
 "sites": [
  {
   "site_id": 1,
   "latitude": 16.82500197195929,
   "longitude": 83.28324580708157,
   "composition": "iron"
  },
  {
   "site_id": 2,
   "latitude": 17.132303202109235,
   "longitude": 83.26820739862481,
   "composition": "iron"
  },
  {
   "site_id": 3,
   "latitude": 17.8425371019334,
   "longitude": 83.9464944033123,
   "composition": "stony-iron"
  },
  {
   "site_id": 4,
   "latitude": 16.816282200903327,
   "longitude": 82.42048044156314,
   "composition": "stony-iron"
  },
  {
   "site_id": 5,
   "latitude": 16.735199532776164,
   "longitude": 82.70961749443457,
   "composition": "iron"
  }
 ]
}